candor/__init__.py
candor/candor.py
candor-1.0.dist-info/METADATA
candor-1.0.dist-info/WHEEL
candor-1.0.dist-info/top_level.txt
candor-1.0.dist-info/RECORD
