Metadata-Version: 2.1
Name: candor
Version: 1.0
Summary: Python Library for Candor Services' Project Mercury API.
Home-page: https://github.com/candorservices/candor-py
Author: FroostySnoowman
Author-email: froostysnoowmanbusiness@gmail.com
Requires-Dist: requests
